justit_vishalkumar014/__init__.py
justit_vishalkumar014/core.py
Jusit-0.0.1.dist-info/LICENSE
Jusit-0.0.1.dist-info/METADATA
Jusit-0.0.1.dist-info/WHEEL
Jusit-0.0.1.dist-info/top_level.txt
Jusit-0.0.1.dist-info/RECORD
