Metadata-Version: 2.1
Name: Jusit
Version: 0.0.1
Summary: A Just it
Author-email: Vishal kumar <vishalkumar049022@gmail.com>
Project-URL: Homepage, https://github.com/Vishalkumar01421/justit
Project-URL: Bug Tracker, https://github.com/Vishalkumar01421/justit/issues
Classifier: Programming Language :: Python :: 3
Classifier: License :: OSI Approved :: MIT License
Classifier: Operating System :: OS Independent
Requires-Python: >=3.10
License-File: LICENSE
